Metadata-Version: 1.2
Name: hxl-upload
Version: 6.1.1
Summary: upload file
Home-page: UNKNOWN
Author: hxl
Maintainer: hxl
License: MIT License
Platform: UNKNOWN
Classifier: Programming Language :: Python :: 3
Classifier: License :: OSI Approved :: MIT License
Classifier: Operating System :: OS Independent
